MANIFEST.in
README.md
setup.py
dash_hamburger/Icon.py
dash_hamburger/__init__.py
dash_hamburger/_imports_.py
dash_hamburger/dash_hamburger.dev.js
dash_hamburger/dash_hamburger.min.js
dash_hamburger/metadata.json
dash_hamburger/package.json
dash_hamburger.egg-info/PKG-INFO
dash_hamburger.egg-info/SOURCES.txt
dash_hamburger.egg-info/dependency_links.txt
dash_hamburger.egg-info/top_level.txt