Metadata-Version: 1.0
Name: dash-hamburger
Version: 0.0.1
Summary: A hamburger icon to be used within dash-toggler 
Home-page: UNKNOWN
Author: Zeke Ayonrinde zeke.ayonrinde@15gifts.com
Author-email: UNKNOWN
License: MIT
Platform: UNKNOWN
